tofunc/__init__.py
tofunc/core/__init__.py
tofunc/tests/__init__.py
tofunc/tests/test_hello.py
tofunc-1.0.1.dist-info/licenses/LICENSE.txt
tofunc-1.0.1.dist-info/METADATA
tofunc-1.0.1.dist-info/WHEEL
tofunc-1.0.1.dist-info/top_level.txt
tofunc-1.0.1.dist-info/RECORD
